jcli/__init__.py
jcli/cli.py
jcli/config.py
jcli/version.py
jenkins_job_cli-0.3.8.dist-info/LICENSE
jenkins_job_cli-0.3.8.dist-info/METADATA
jenkins_job_cli-0.3.8.dist-info/WHEEL
jenkins_job_cli-0.3.8.dist-info/entry_points.txt
jenkins_job_cli-0.3.8.dist-info/RECORD
